markdown2html/__init__.py
markdown2html/markdown.py
markdown2html/md.py
markd2html-0.0.0.dist-info/LICENSE
markd2html-0.0.0.dist-info/METADATA
markd2html-0.0.0.dist-info/WHEEL
markd2html-0.0.0.dist-info/entry_points.txt
markd2html-0.0.0.dist-info/top_level.txt
markd2html-0.0.0.dist-info/RECORD
