Metadata-Version: 2.1
Name: markd2html
Version: 0.0.0
Summary: markd2html is a package to convert Github Markdown syntax to Html
Home-page: https://github.com/saarikabhasi/markdown-to-html
Author: Saarika
Author-email: saarikabhasi@yahoo.com
License: UNKNOWN
Project-URL: Bug Tracker, https://github.com/saarikabhasi/markdown-to-html/issues
Platform: UNKNOWN
Classifier: Programming Language :: Python :: 3
Classifier: License :: OSI Approved :: MIT License
Classifier: Operating System :: OS Independent
License-File: LICENSE
